jaide/__init__.py
jaide/cli.py
jaide/color_utils.py
jaide/core.py
jaide/errors.py
jaide/utils.py
jaide/wrap.py
jaide-2.0.0.dist-info/DESCRIPTION.rst
jaide-2.0.0.dist-info/entry_points.txt
jaide-2.0.0.dist-info/METADATA
jaide-2.0.0.dist-info/metadata.json
jaide-2.0.0.dist-info/RECORD
jaide-2.0.0.dist-info/top_level.txt
jaide-2.0.0.dist-info/WHEEL
