Metadata-Version: 2.0
Name: jaide
Version: 2.0.0
Summary: A library and CLI tool for manipulating Junos devices.
Home-page: https://github.com/NetworkAutomation/jaide
Author: Nathan Printz <nkprintz@gmail.com> and Geoff Rhodes <geofflrhodes@gmail.com>
Author-email: nkprintz@gmail.com
License: GNU GPL
Keywords: networking junos juniper
Platform: UNKNOWN
Classifier: Development Status :: 4 - Beta
Classifier: Intended Audience :: Developers
Classifier: Intended Audience :: Information Technology
Classifier: Intended Audience :: Telecommunications Industry
Classifier: Intended Audience :: System Administrators
Classifier: Topic :: System :: Networking
Classifier: Topic :: System :: Systems Administration
Classifier: Topic :: Utilities
Classifier: License :: OSI Approved :: GNU General Public License v2 (GPLv2)
Classifier: Programming Language :: Python
Classifier: Programming Language :: Python :: 2
Classifier: Programming Language :: Python :: 2.7
Classifier: Natural Language :: English
Requires-Dist: click (>=4.0.0,<5.0.0)
Requires-Dist: colorama (>0.3.2)
Requires-Dist: ncclient (>=0.4.2)
Requires-Dist: paramiko (>=1.14.0,<2.0.0)
Requires-Dist: scp (>=0.8.0,<1.0.0)
Requires-Dist: ecdsa (>=0.11)
Requires-Dist: pycrypto (>=2.1,!=2.4)
